setup.py
bin/dboxsync
dboxsync/__init__.py
dboxsync.egg-info/PKG-INFO
dboxsync.egg-info/SOURCES.txt
dboxsync.egg-info/dependency_links.txt
dboxsync.egg-info/requires.txt
dboxsync.egg-info/top_level.txt