Metadata-Version: 1.0
Name: dboxsync
Version: 0.1
Summary: Syncs a Dropbox file or folder locally
Home-page: UNKNOWN
Author: Maxime Bouroumeau-Fuseau
Author-email: maxime.bouroumeau@gmail.com
License: UNKNOWN
Platform: UNKNOWN
